whosclient/__init__.py
whosclient/__main__.py
whosclient/whosclient.py
whosclient-0.1.2.dist-info/METADATA
whosclient-0.1.2.dist-info/WHEEL
whosclient-0.1.2.dist-info/entry_points.txt
whosclient-0.1.2.dist-info/top_level.txt
whosclient-0.1.2.dist-info/RECORD
