Metadata-Version: 2.4
Name: whosclient
Version: 0.1.2
Author-email: Instituto Nacional del Agua <jbianchi@ina.gob.ar>
Requires-Dist: click
Requires-Dist: requests
Requires-Dist: pandas
Requires-Dist: plotly
Requires-Dist: nbformat
